[
  {
    "title": "Gestione Lavori Web Riunioni",
    "description": "SUM",
    "start": "2022-02-11 09:15:00",
    "durata": "0.25",
    "id_interventi": "273208",
    "ore_spostamento": "0",
    "km_spostamento": "0",
    "color": "#bbbbdd",
    "end": "2022-02-11 09:30:00"
  },
  {
    "title": "Opacmare Assistenza Accounting",
    "description": "supporto al cliente e riconfigurazione DNS che erano saltati (lato loro)",
    "start": "2022-02-11 09:30:00",
    "durata": "0.25",
    "id_interventi": "270522",
    "ore_spostamento": "0",
    "km_spostamento": "0",
    "color": "#bbffbb",
    "end": "2022-02-11 09:45:00"
  },
  {
    "title": "ARO SpA Assistenza annuale",
    "description": "Verifica sync su stage",
    "start": "2022-02-11 09:45:00",
    "durata": "0.25",
    "id_interventi": "270531",
    "ore_spostamento": "0",
    "km_spostamento": "0",
    "color": "#ddddbb",
    "end": "2022-02-11 10:00:00"
  },
  {
    "title": "Gestione Lavori Web Controllo di gestione",
    "description": "",
    "start": "2022-02-11 10:00:00",
    "durata": "3.25",
    "id_interventi": "273207",
    "ore_spostamento": "0",
    "km_spostamento": "0",
    "color": "#bbffdd",
    "end": "2022-02-11 13:15:00"
  },
  {
    "title": "Gestione Azienda Riunioni",
    "description": "riunione devops",
    "start": "2022-02-11 14:30:00",
    "durata": "4",
    "id_interventi": "270634",
    "ore_spostamento": "0",
    "km_spostamento": "0",
    "color": "#bbbbdd",
    "end": "2022-02-11 18:30:00"
  },
  {
    "title": "Gestione Lavori Web Controllo di gestione",
    "description": "passate cose a nikolas",
    "start": "2022-02-14 09:00:00",
    "durata": "0.5",
    "id_interventi": "271197",
    "ore_spostamento": "0",
    "km_spostamento": "0",
    "color": "#bbffdd",
    "end": "2022-02-14 09:30:00"
  },
  {
    "title": "ARO SpA Assistenza annuale",
    "description": "verifica server",
    "start": "2022-02-14 09:30:00",
    "durata": "0.25",
    "id_interventi": "271201",
    "ore_spostamento": "0",
    "km_spostamento": "0",
    "color": "#ddddbb",
    "end": "2022-02-14 09:45:00"
  },
  {
    "title": "ForIndustry Assitenza Accounting",
    "description": "call cliente e verifica con leti",
    "start": "2022-02-14 09:45:00",
    "durata": "1.75",
    "id_interventi": "270959",
    "ore_spostamento": "0",
    "km_spostamento": "0",
    "color": "#bbffbb",
    "end": "2022-02-14 11:30:00"
  },
  {
    "title": "Pause e permessi Pausa",
    "description": "",
    "start": "2022-02-14 11:30:00",
    "durata": "0.25",
    "id_interventi": "271202",
    "ore_spostamento": "0",
    "km_spostamento": "0",
    "color": "#ffbbbb",
    "end": "2022-02-14 11:45:00"
  },
  {
    "title": "Gestione Azienda Telefonate/email",
    "description": "tel varie",
    "start": "2022-02-14 11:45:00",
    "durata": "0.25",
    "id_interventi": "271203",
    "ore_spostamento": "0",
    "km_spostamento": "0",
    "color": "#bbbbdd",
    "end": "2022-02-14 12:00:00"
  },
  {
    "title": "Commerciale Web Analisi nuovi lavori",
    "description": "Call Rekico",
    "start": "2022-02-14 12:00:00",
    "durata": "1",
    "id_interventi": "270960",
    "ore_spostamento": "0",
    "km_spostamento": "0",
    "color": "#ffffbb",
    "end": "2022-02-14 13:00:00"
  },
  {
    "title": "Order Sender Analisi",
    "description": "Discusso di modifiche su BT",
    "start": "2022-02-14 14:00:00",
    "durata": "0.5",
    "id_interventi": "271194",
    "ore_spostamento": "0",
    "km_spostamento": "0",
    "color": "#ffffbb",
    "end": "2022-02-14 14:30:00"
  },
  {
    "title": "Nimax Assistenza Accounting",
    "description": "tel Cloro",
    "start": "2022-02-14 14:30:00",
    "durata": "0.5",
    "id_interventi": "271200",
    "ore_spostamento": "0",
    "km_spostamento": "0",
    "color": "#bbffbb",
    "end": "2022-02-14 15:00:00"
  },
  {
    "title": "Paginae Debugging",
    "description": "verifica con giulia funzionamento gestione bundle",
    "start": "2022-02-14 15:00:00",
    "durata": "0.75",
    "id_interventi": "271199",
    "ore_spostamento": "0",
    "km_spostamento": "0",
    "color": "#bbddff",
    "end": "2022-02-14 15:45:00"
  },
  {
    "title": "Ufficio Acquisti",
    "description": "licenza active collab",
    "start": "2022-02-14 15:45:00",
    "durata": "0.25",
    "id_interventi": "271198",
    "ore_spostamento": "0",
    "km_spostamento": "0",
    "color": "#ffffbb",
    "end": "2022-02-14 16:00:00"
  },
  {
    "title": "Astidental Assistenza Assistenza Sito",
    "description": "verifica lavoro Nikolas",
    "start": "2022-02-14 16:00:00",
    "durata": "0.25",
    "id_interventi": "271196",
    "ore_spostamento": "0",
    "km_spostamento": "0",
    "color": "#ddbbff",
    "end": "2022-02-14 16:15:00"
  },
  {
    "title": "ARO SpA Assistenza annuale",
    "description": "debug sistema",
    "start": "2022-02-14 16:15:00",
    "durata": "0.25",
    "id_interventi": "271195",
    "ore_spostamento": "0",
    "km_spostamento": "0",
    "color": "#ddddbb",
    "end": "2022-02-14 16:30:00"
  },
  {
    "title": "OSB Release #1-2022 Analisi",
    "description": "con jumpy discusso di come ottimizzare gli ordini",
    "start": "2022-02-14 16:30:00",
    "durata": "1",
    "id_interventi": "271193",
    "ore_spostamento": "0",
    "km_spostamento": "0",
    "color": "#ffffbb",
    "end": "2022-02-14 17:30:00"
  },
  {
    "title": "Novalux assistenza Assistenza annuale",
    "description": "attivazione filebrowser",
    "start": "2022-02-14 17:30:00",
    "durata": "0.25",
    "id_interventi": "271192",
    "ore_spostamento": "0",
    "km_spostamento": "0",
    "color": "#ddddbb",
    "end": "2022-02-14 17:45:00"
  },
  {
    "title": "Astidental Assistenza Set Prodotti",
    "description": "sistemazione margini",
    "start": "2022-02-14 17:45:00",
    "durata": "0.25",
    "id_interventi": "271191",
    "ore_spostamento": "0",
    "km_spostamento": "0",
    "color": "#ddbbff",
    "end": "2022-02-14 18:00:00"
  },
  {
    "title": "Gestione Lavori Web Controllo di gestione",
    "description": "SUM",
    "start": "2022-02-15 09:15:00",
    "durata": "0.25",
    "id_interventi": "271188",
    "ore_spostamento": "0",
    "km_spostamento": "0",
    "color": "#bbffdd",
    "end": "2022-02-15 09:30:00"
  },
  {
    "title": "Chaberton Integrazioni Sito Accounting",
    "description": "attivazione cookiebot",
    "start": "2022-02-15 09:30:00",
    "durata": "0.25",
    "id_interventi": "271189",
    "ore_spostamento": "0",
    "km_spostamento": "0",
    "color": "#bbffbb",
    "end": "2022-02-15 09:45:00"
  },
  {
    "title": "Gestione Lavori Web Controllo di gestione",
    "description": "con nikolas e verifica lavori vari",
    "start": "2022-02-15 09:45:00",
    "durata": "0.75",
    "id_interventi": "271190",
    "ore_spostamento": "0",
    "km_spostamento": "0",
    "color": "#bbffdd",
    "end": "2022-02-15 10:30:00"
  },
  {
    "title": "Astidental Assistenza Set Prodotti",
    "description": "verifiche sui costi",
    "start": "2022-02-15 10:30:00",
    "durata": "1",
    "id_interventi": "270956",
    "ore_spostamento": "0",
    "km_spostamento": "0",
    "color": "#ddbbff",
    "end": "2022-02-15 11:30:00"
  },
  {
    "title": "Bondioli & Pavesi Categora: analisi Analisi",
    "description": "analisi interna",
    "start": "2022-02-15 11:30:00",
    "durata": "1.75",
    "id_interventi": "270955",
    "ore_spostamento": "0",
    "km_spostamento": "0",
    "color": "#ffffbb",
    "end": "2022-02-15 13:15:00"
  },
  {
    "title": "Bondioli & Pavesi Categora: analisi Analisi",
    "description": "call cliente",
    "start": "2022-02-15 14:00:00",
    "durata": "3",
    "id_interventi": "270953",
    "ore_spostamento": "0",
    "km_spostamento": "0",
    "color": "#ffffbb",
    "end": "2022-02-15 17:00:00"
  },
  {
    "title": "Gestione Azienda Riunioni",
    "description": "soci",
    "start": "2022-02-15 17:00:00",
    "durata": "1.5",
    "id_interventi": "270954",
    "ore_spostamento": "0",
    "km_spostamento": "0",
    "color": "#bbbbdd",
    "end": "2022-02-15 18:30:00"
  },
  {
    "title": "Ufficio IT Esterno",
    "description": "problematiche gimli e hangon",
    "start": "2022-02-15 18:30:00",
    "durata": "0.5",
    "id_interventi": "270961",
    "ore_spostamento": "0",
    "km_spostamento": "0",
    "color": "#ffffbb",
    "end": "2022-02-15 19:00:00"
  },
  {
    "title": "Paginae Sviluppo Web",
    "description": "impostata gestione bundle",
    "start": "2022-02-15 19:00:00",
    "durata": "0.25",
    "id_interventi": "270963",
    "ore_spostamento": "0",
    "km_spostamento": "0",
    "color": "#bbddff",
    "end": "2022-02-15 19:15:00"
  },
  {
    "title": "Commerciale Web Analisi nuovi lavori",
    "description": "mail rekico",
    "start": "2022-02-15 19:15:00",
    "durata": "0.25",
    "id_interventi": "270962",
    "ore_spostamento": "0",
    "km_spostamento": "0",
    "color": "#ffffbb",
    "end": "2022-02-15 19:30:00"
  },
  {
    "title": "Gestione Lavori Riordino email",
    "description": "",
    "start": "2022-02-16 09:00:00",
    "durata": "0.25",
    "id_interventi": "271187",
    "ore_spostamento": "0",
    "km_spostamento": "0",
    "color": "#bbffdd",
    "end": "2022-02-16 09:15:00"
  },
  {
    "title": "Gestione Lavori Web Riunioni",
    "description": "SUM",
    "start": "2022-02-16 09:15:00",
    "durata": "0.5",
    "id_interventi": "271186",
    "ore_spostamento": "0",
    "km_spostamento": "0",
    "color": "#bbbbdd",
    "end": "2022-02-16 09:45:00"
  },
  {
    "title": "Gestione Risorse Umane Colloqui interni",
    "description": "con Fabio Cosenza",
    "start": "2022-02-16 09:45:00",
    "durata": "0.5",
    "id_interventi": "271185",
    "ore_spostamento": "0",
    "km_spostamento": "0",
    "color": "#bbbbdd",
    "end": "2022-02-16 10:15:00"
  },
  {
    "title": "Centro Gamma Assistenza annuale",
    "description": "verifica problema download",
    "start": "2022-02-16 10:15:00",
    "durata": "0.25",
    "id_interventi": "271184",
    "ore_spostamento": "0",
    "km_spostamento": "0",
    "color": "#ddddbb",
    "end": "2022-02-16 10:30:00"
  },
  {
    "title": "Novalux assistenza Assistenza annuale",
    "description": "preparazione dati per traduzione",
    "start": "2022-02-16 10:30:00",
    "durata": "0.5",
    "id_interventi": "271183",
    "ore_spostamento": "0",
    "km_spostamento": "0",
    "color": "#ddddbb",
    "end": "2022-02-16 11:00:00"
  },
  {
    "title": "Novalux SLV e contatti Analisi",
    "description": "Call Novalux per nuove integrazioni",
    "start": "2022-02-16 11:00:00",
    "durata": "2",
    "id_interventi": "271053",
    "ore_spostamento": "0",
    "km_spostamento": "0",
    "color": "#ffffbb",
    "end": "2022-02-16 13:00:00"
  },
  {
    "title": "Commerciale Web Analisi nuovi lavori",
    "description": "Lucano Progetto Categora https://us06web.zoom.us/j/82467871556?pwd=aEtxeVNXNlRna1lEejY0djZUSWZOdz09",
    "start": "2022-02-16 14:30:00",
    "durata": "1.5",
    "id_interventi": "271099",
    "ore_spostamento": "0",
    "km_spostamento": "0",
    "color": "#ffffbb",
    "end": "2022-02-16 16:00:00"
  },
  {
    "title": "Gestione Lavori Web Controllo di gestione",
    "description": "Call interna Novalux con Benedetta e Alessandro",
    "start": "2022-02-16 16:00:00",
    "durata": "1.5",
    "id_interventi": "271100",
    "ore_spostamento": "0",
    "km_spostamento": "0",
    "color": "#bbffdd",
    "end": "2022-02-16 17:30:00"
  },
  {
    "title": "Master in Fundraising Assistenza annuale",
    "description": "verifica problema mailup e preparazione alla migrazione",
    "start": "2022-02-16 17:30:00",
    "durata": "1",
    "id_interventi": "271182",
    "ore_spostamento": "0",
    "km_spostamento": "0",
    "color": "#ddddbb",
    "end": "2022-02-16 18:30:00"
  },
  {
    "title": "ForIndustry Assitenza Accounting",
    "description": "verifica task",
    "start": "2022-02-17 09:00:00",
    "durata": "0.5",
    "id_interventi": "271279",
    "ore_spostamento": "0",
    "km_spostamento": "0",
    "color": "#bbffbb",
    "end": "2022-02-17 09:30:00"
  },
  {
    "title": "Gestione Lavori Web Riunioni",
    "description": "SUM",
    "start": "2022-02-17 09:30:00",
    "durata": "0.25",
    "id_interventi": "271280",
    "ore_spostamento": "0",
    "km_spostamento": "0",
    "color": "#bbbbdd",
    "end": "2022-02-17 09:45:00"
  },
  {
    "title": "Gestione Lavori Web Controllo di gestione",
    "description": "organizzazione attivit\u00e0",
    "start": "2022-02-17 09:45:00",
    "durata": "0.25",
    "id_interventi": "271281",
    "ore_spostamento": "0",
    "km_spostamento": "0",
    "color": "#bbffdd",
    "end": "2022-02-17 10:00:00"
  },
  {
    "title": "Commerciale Web Analisi nuovi lavori",
    "description": "con fabio analisi richeiste novalux",
    "start": "2022-02-17 10:00:00",
    "durata": "0.5",
    "id_interventi": "271277",
    "ore_spostamento": "0",
    "km_spostamento": "0",
    "color": "#ffffbb",
    "end": "2022-02-17 10:30:00"
  },
  {
    "title": "Tempocasa Categora Accounting",
    "description": "call",
    "start": "2022-02-17 10:30:00",
    "durata": "0.25",
    "id_interventi": "271278",
    "ore_spostamento": "0",
    "km_spostamento": "0",
    "color": "#bbffbb",
    "end": "2022-02-17 10:45:00"
  },
  {
    "title": "Commerciale Web Analisi nuovi lavori",
    "description": "prev novalux",
    "start": "2022-02-17 10:45:00",
    "durata": "0.5",
    "id_interventi": "271282",
    "ore_spostamento": "0",
    "km_spostamento": "0",
    "color": "#ffffbb",
    "end": "2022-02-17 11:15:00"
  },
  {
    "title": "Nimax Assistenza Analisi e supporto",
    "description": "tel e fix offerta",
    "start": "2022-02-17 11:15:00",
    "durata": "0.5",
    "id_interventi": "271276",
    "ore_spostamento": "0",
    "km_spostamento": "0",
    "color": "#ffffbb",
    "end": "2022-02-17 11:45:00"
  },
  {
    "title": "Pause e permessi Permesso",
    "description": "Permesso",
    "start": "2022-02-17 11: 45: 00",
    "durata": "1",
    "id_interventi": "271052",
    "ore_spostamento": "0",
    "km_spostamento": "0",
    "color": "#ffbbbb",
    "end": "2022-02-17 12: 45: 00"
  },
  {
    "title": "Commerciale Web Preventivo",
    "description": "prev vari",
    "start": "2022-02-17 12: 45: 00",
    "durata": "1",
    "id_interventi": "271275",
    "ore_spostamento": "0",
    "km_spostamento": "0",
    "color": "#ffddbb",
    "end": "2022-02-17 13: 45: 00"
  },
  {
    "title": "Master in Fundraising Assistenza annuale",
    "description": "preparazione alla migrazione",
    "start": "2022-02-17 15: 00: 00",
    "durata": "0.5",
    "id_interventi": "273771",
    "ore_spostamento": "0",
    "km_spostamento": "0",
    "color": "#ddddbb",
    "end": "2022-02-17 15: 30: 00"
  },
  {
    "title": "Equiline ecommerce B2B e PIM Categora Accounting",
    "description": "call interna e call con il cliente",
    "start": "2022-02-17 15: 30: 00",
    "durata": "3.5",
    "id_interventi": "273765",
    "ore_spostamento": "0",
    "km_spostamento": "0",
    "color": "#bbffbb",
    "end": "2022-02-17 19: 00: 00"
  },
  {
    "title": "Master in Fundraising Assistenza annuale",
    "description": "migrazione del server",
    "start": "2022-02-17 19: 00: 00",
    "durata": "2",
    "id_interventi": "273761",
    "ore_spostamento": "0",
    "km_spostamento": "0",
    "color": "#ddddbb",
    "end": "2022-02-17 21: 00: 00"
  },
  {
    "title": "Gestione Lavori Web Controllo di gestione",
    "description": "punti vari",
    "start": "2022-02-18 09: 00: 00",
    "durata": "0.5",
    "id_interventi": "273778",
    "ore_spostamento": "0",
    "km_spostamento": "0",
    "color": "#bbffdd",
    "end": "2022-02-18 09: 30: 00"
  },
  {
    "title": "Novalux Sito 2021 Accounting",
    "description": "Call Novalux https://us06web.zoom.us/j/89054709556?pwd=ZjVRTnpLaS91OXc1ME5WdGk4U1paUT09\n\nID riunione: 890 5470 9556\nPasscode: 200288",
    "start": "2022-02-18 09:30:00",
    "durata": "0.5",
    "id_interventi": "272054",
    "ore_spostamento": "0",
    "km_spostamento": "0",
    "color": "#bbffbb",
    "end": "2022-02-18 10:00:00"
  },
  {
    "title": "Gestione Azienda Riunioni",
    "description": "giorgio in ufficio, tel varie",
    "start": "2022-02-18 10:00:00",
    "durata": "2",
    "id_interventi": "273782",
    "ore_spostamento": "0",
    "km_spostamento": "0",
    "color": "#bbbbdd",
    "end": "2022-02-18 12:00:00"
  },
  {
    "title": "Master in Fundraising Assistenza annuale",
    "description": "verifiche post migrazione",
    "start": "2022-02-18 12:00:00",
    "durata": "0.5",
    "id_interventi": "273780",
    "ore_spostamento": "0",
    "km_spostamento": "0",
    "color": "#ddddbb",
    "end": "2022-02-18 12:30:00"
  },
  {
    "title": "Astidental Assistenza Set Prodotti",
    "description": "verifiche con gianoglio",
    "start": "2022-02-18 12:30:00",
    "durata": "0.5",
    "id_interventi": "273779",
    "ore_spostamento": "0",
    "km_spostamento": "0",
    "color": "#ddbbff",
    "end": "2022-02-18 13:00:00"
  },
  {
    "title": "Commerciale Web Contatto cliente",
    "description": "Call con Lavorgomma Qui il link per la nostra call: https://meet.google.com/xrh-tctr-pjp",
    "start": "2022-02-18 14:00:00",
    "durata": "1",
    "id_interventi": "272055",
    "ore_spostamento": "0",
    "km_spostamento": "0",
    "color": "#ffddbb",
    "end": "2022-02-18 15:00:00"
  },
  {
    "title": "ARO SpA Assistenza annuale",
    "description": "verifica problema segnalato dal cliente",
    "start": "2022-02-18 15:00:00",
    "durata": "1",
    "id_interventi": "273783",
    "ore_spostamento": "0",
    "km_spostamento": "0",
    "color": "#ddddbb",
    "end": "2022-02-18 16:00:00"
  },
  {
    "title": "Commerciale Web Contatto cliente",
    "description": "mail varie e allineamento pipedrive",
    "start": "2022-02-18 16:00:00",
    "durata": "0.5",
    "id_interventi": "273784",
    "ore_spostamento": "0",
    "km_spostamento": "0",
    "color": "#ffddbb",
    "end": "2022-02-18 16:30:00"
  },
  {
    "title": "Commerciale Web Analisi nuovi lavori",
    "description": "stime euroscreen e sherwin williams",
    "start": "2022-02-18 16:30:00",
    "durata": "1.5",
    "id_interventi": "273785",
    "ore_spostamento": "0",
    "km_spostamento": "0",
    "color": "#ffffbb",
    "end": "2022-02-18 18:00:00"
  }
]